LICENSE
MANIFEST.in
README.rst
setup.py
nose_alert.egg-info/PKG-INFO
nose_alert.egg-info/SOURCES.txt
nose_alert.egg-info/dependency_links.txt
nose_alert.egg-info/entry_points.txt
nose_alert.egg-info/requires.txt
nose_alert.egg-info/top_level.txt
nosealert/__init__.py
nosealert/notifications.py
nosealert/platform.py
nosealert/plugin.py
nosealert/images/dialog-error.png
nosealert/images/dialog-ok.png
nosealert/tests/__init__.py
nosealert/tests/test_notifications.py
nosealert/tests/test_platform.py
nosealert/tests/test_plugin.py