Metadata-Version: 1.1
Name: nose-alert
Version: 0.9.1
Summary: 
